devopso
