Metadata-Version: 2.4
Name: devops-overseer
Version: 0.0.3
Summary: DevOps overseer to manage process automations and conformity
Author-email: mot0ko <dourval.clement@gmail.com>
License: MIT License
Project-URL: Homepage, https://github.com/mot0ko/devops.overseer
Project-URL: Source, https://github.com/mot0ko/devops.overseer
Project-URL: Issues, https://github.com/mot0ko/devops.overseer/issues
Requires-Python: >=3.9
License-File: LICENSE
Requires-Dist: python-dateutil>=2.9.0
Requires-Dist: requests>=2.32.5
Requires-Dist: pydantic>=2.12.1
Requires-Dist: pyyaml>=6.0.2
Dynamic: license-file
